CHANGES.txt
CONTRIBUTORS.txt
README.txt
bootstrap.py
buildout.cfg
setup.cfg
setup.py
cns/__init__.py
cns.recipe.symlink.egg-info/PKG-INFO
cns.recipe.symlink.egg-info/SOURCES.txt
cns.recipe.symlink.egg-info/dependency_links.txt
cns.recipe.symlink.egg-info/entry_points.txt
cns.recipe.symlink.egg-info/namespace_packages.txt
cns.recipe.symlink.egg-info/not-zip-safe
cns.recipe.symlink.egg-info/requires.txt
cns.recipe.symlink.egg-info/top_level.txt
cns/recipe/__init__.py
cns/recipe/symlink/__init__.py
cns/recipe/symlink/tests/__init__.py
cns/recipe/symlink/tests/test_docs.py
docs/Makefile
docs/README.txt
docs/conf.py
docs/index.txt