Metadata-Version: 1.0
Name: cns.recipe.symlink
Version: 0.2.3
Summary: UNKNOWN
Home-page: http://github.com/koodaamo/cns.recipe.symlink
Author: Radim Novotny, Petri Savolainen
Author-email: novotny.radim@gmail.com, petri.savolainen@koodaamo.fi
License: GPL
Keywords: buildout
Platform: UNKNOWN
Classifier: Framework :: Buildout
Classifier: Intended Audience :: Developers
Classifier: Topic :: Software Development :: Build Tools
Classifier: License :: OSI Approved :: Zope Public License
